{
  "detector_count": 2,
  "detectors": [
    {
      "description": "Flags primitive-like values written into _active_models, which breaks the loaded-model registry contract for get_active_model().",
      "detector_id": "correctness.active-model-primitive-store",
      "rule_class": "correctness"
    },
    {
      "description": "Flags object.__setattr__ writes to StageContext validated fields that bypass the assignment-time path-traversal guard.",
      "detector_id": "correctness.stage-context-validation-bypass",
      "rule_class": "correctness"
    }
  ],
  "finding_count": 0,
  "findings": [],
  "format_version": 1,
  "root": "."
}
